selenium_library/__init__.py
selenium_library/base.py
selenium_library-0.0.3.dist-info/METADATA
selenium_library-0.0.3.dist-info/WHEEL
selenium_library-0.0.3.dist-info/top_level.txt
selenium_library-0.0.3.dist-info/RECORD
