Metadata-Version: 2.1
Name: selenium_library
Version: 0.0.3
Summary: A human readable wrapper class for selenium
Home-page: https://github.com/janmarkuslanger/selenium-library
Author: Jan-Markus Langer
Author-email: janmarkuslanger10121994@gmail.com
License: UNKNOWN
Platform: UNKNOWN
Classifier: Programming Language :: Python :: 3
Classifier: License :: OSI Approved :: MIT License
Classifier: Operating System :: OS Independent
Requires-Python: >=3.6
